sparklingasterisk-0.1.0.dist-info/METADATA
sparklingasterisk-0.1.0.dist-info/WHEEL
sparklingasterisk/__init__.py
sparklingasterisk/_core.abi3.so
sparklingasterisk/_core.pyi
sparklingasterisk/differential/__init__.py
sparklingasterisk/differential/discrete.py
sparklingasterisk/py.typed
sparklingasterisk-0.1.0.dist-info/RECORD
