Metadata-Version: 2.4
Name: sparklingasterisk
Version: 0.1.0
Requires-Dist: twine>=6.1.0
Summary: Add your description here
Author-email: sparklingasteriskgh <rahulbhadani@email.arizona.edu>
Requires-Python: >=3.12
